openwebpos/__init__.py
openwebpos-0.0.4.dist-info/LICENSE
openwebpos-0.0.4.dist-info/METADATA
openwebpos-0.0.4.dist-info/WHEEL
openwebpos-0.0.4.dist-info/top_level.txt
openwebpos-0.0.4.dist-info/RECORD
