Metadata-Version: 2.1
Name: openwebpos
Version: 0.0.4
Summary: Web-based point of sale system.
Home-page: https://github.com/baezfb/openwebpos
Author: Javier Baez
Author-email: baezdevs@gmail.com
License: MIT
Keywords: python,pos,point-of-sale
Platform: UNKNOWN
Classifier: Development Status :: 1 - Planning
Classifier: Intended Audience :: Developers
Classifier: Framework :: Flask
Classifier: Programming Language :: Python :: 3
Classifier: Programming Language :: Python :: 3.8
Classifier: Programming Language :: Python :: 3.9
Classifier: License :: OSI Approved :: MIT License
Classifier: Operating System :: OS Independent
License-File: LICENSE
Requires-Dist: flask (~=2.0)
Provides-Extra: dev
